{
  "errcode": 0,
  "errmsg": "",
  "data": {
    "fuhuadetails": [
      {
        "incubation_id": "1",
        "project_name": "园区项目技术孵化",
        "company_register_date":"2010021",
        "company_name":"借贷",
        "statues":"1",
        "company_register_address":"企业陈小春注册地址",
        "office_address":"办公地址",
        "company_nature_name": "企业性质名称",
        "technique_field_name":"技术领域名称",
        "register_capital":"111111，整数，单位万",
        "employee_count":"10%",
        "business_licence":"咕咕咕咕",
        "contact_name":"联系人姓名",
        "contact_mobile":"联系人手机",
        "contact_email": "联系人邮箱",
        "company_business_scope":"你猜",
        "company_desc":"公巨化股份第三的风格司介绍"

      }
    ]
  }
}